find_gcp_keys/__init__.py
find_gcp_keys/__main__.py
find_gcp_keys-0.6.2.dist-info/LICENSE
find_gcp_keys-0.6.2.dist-info/METADATA
find_gcp_keys-0.6.2.dist-info/WHEEL
find_gcp_keys-0.6.2.dist-info/entry_points.txt
find_gcp_keys-0.6.2.dist-info/top_level.txt
find_gcp_keys-0.6.2.dist-info/RECORD
