Metadata-Version: 2.1
Name: find-gcp-keys
Version: 0.6.2
Summary: Find and report valid Google Service Account keys on your filesystem
Home-page: https://github.com/dinvlad/find-gcp-keys
Author: Denis Loginov
License: BSD 3-clause "New" or "Revised" License
Platform: UNKNOWN
Classifier: Development Status :: 3 - Alpha
Classifier: License :: OSI Approved :: BSD License
Classifier: Operating System :: OS Independent
Classifier: Programming Language :: Python :: 3 :: Only
Classifier: Topic :: Security
Classifier: Topic :: Security :: Cryptography
Classifier: Topic :: Utilities
Requires-Python: >=3.7.0
Requires-Dist: google-auth (>=1.21.0)
